bin/__init__.py
bin/csv2json.py
bin/evaluate.py
bin/export_model.py
bin/grad_analysis.py
bin/prep_embedding_dataset.py
bin/prepare_corpus.py
bin/prepare_ved_corpus.py
bin/print_covariate_model.py
bin/select_model.py
bin/select_sb_model.py
bin/seq_vae.py
bin/train_embeddings.py
bin/train_model.py
bin/train_sb_ved.py
tmnt/__init__.py
tmnt/bert_handling.py
tmnt/common_params.py
tmnt/configuration.py
tmnt/data_loading.py
tmnt/distribution.py
tmnt/estimator.py
tmnt/eval_npmi.py
tmnt/inference.py
tmnt/modeling.py
tmnt/selector.py
tmnt/trainer.py
tmnt/classifier/__init__.py
tmnt/classifier/load_data.py
tmnt/classifier/model.py
tmnt/classifier/train_sparse.py
tmnt/distributions/__init__.py
tmnt/distributions/gaussian.py
tmnt/distributions/gaussian_fixedvar.py
tmnt/distributions/hypersphere.py
tmnt/distributions/latent_distrib.py
tmnt/distributions/logistic_gaussian.py
tmnt/embeddings/__init__.py
tmnt/embeddings/data.py
tmnt/embeddings/executors.py
tmnt/embeddings/model.py
tmnt/embeddings/train.py
tmnt/preprocess/__init__.py
tmnt/preprocess/preprocessor.py
tmnt/preprocess/tokenizer.py
tmnt/preprocess/vectorizer.py
tmnt/utils/__init__.py
tmnt/utils/csv2json.py
tmnt/utils/log_utils.py
tmnt/utils/mat_utils.py
tmnt/utils/ngram_helpers.py
tmnt/utils/pubmed_utils.py
tmnt/utils/random.py
tmnt/utils/recalibrate.py
tmnt_cu101-0.6.3.dist-info/LICENSE
tmnt_cu101-0.6.3.dist-info/METADATA
tmnt_cu101-0.6.3.dist-info/NOTICE
tmnt_cu101-0.6.3.dist-info/WHEEL
tmnt_cu101-0.6.3.dist-info/top_level.txt
tmnt_cu101-0.6.3.dist-info/RECORD
