Metadata-Version: 2.1
Name: tmnt-cu101
Version: 0.6.3
Summary: Topic modeling neural toolkit
Home-page: https://github.com/mitre/tmnt.git
Author: The MITRE Corporation
Author-email: wellner@mitre.org
License: Apache
Platform: UNKNOWN
Classifier: Programming Language :: Python :: 3
Classifier: License :: OSI Approved :: Apache Software License
Classifier: Operating System :: OS Independent
Requires-Python: >=3.7
Requires-Dist: numpy (<1.20.0,>=1.19.0)
Requires-Dist: gluonnlp (==0.10.0)
Requires-Dist: autogluon.core (==0.2.0)
Requires-Dist: mantichora (==0.9.5)
Requires-Dist: pandas (<2.0)
Requires-Dist: pyLDAvis (==2.1.2)
Requires-Dist: pyOpenSSL (==18.0.0)
Requires-Dist: PySocks (==1.6.8)
Requires-Dist: sacremoses (>=0.0.38)
Requires-Dist: sentence-splitter (==1.4)
Requires-Dist: scikit-learn (>=0.24.1)
Requires-Dist: numba (<=0.52.0)
Requires-Dist: umap-learn (==0.4.6)
Requires-Dist: tabulate (>=0.8.7)
Requires-Dist: mxnet-cu101 (<1.8.0,>=1.6.0)
